[{
  "_id": {
    "$oid": "5f04ed124b9065402096412f"
  },
  "product": null,
  "positionX": 0,
  "positionY": 0,
  "timePlanted": null,
  "garden": {
    "$oid": "5f04ed124b9065402096412e"
  }
},{
  "_id": {
    "$oid": "5f04ed124b90654020964131"
  },
  "product": null,
  "positionX": 1,
  "positionY": 0,
  "timePlanted": null,
  "garden": {
    "$oid": "5f04ed124b9065402096412e"
  }
},{
  "_id": {
    "$oid": "5f04ed124b90654020964133"
  },
  "product": {
    "$oid": "5f04ea394b90654020964129"
  },
  "positionX": 2,
  "positionY": 0,
  "timePlanted": {
    "$date": "2020-07-08T16:11:34.214Z"
  },
  "garden": {
    "$oid": "5f04ed124b9065402096412e"
  }
},{
  "_id": {
    "$oid": "5f04ed124b90654020964135"
  },
  "product": null,
  "positionX": 3,
  "positionY": 0,
  "timePlanted": null,
  "garden": {
    "$oid": "5f04ed124b9065402096412e"
  }
},{
  "_id": {
    "$oid": "5f04ed124b90654020964137"
  },
  "product": {
    "$oid": "5f04ea1d4b90654020964128"
  },
  "positionX": 4,
  "positionY": 0,
  "timePlanted": {
    "$date": "2020-07-08T16:11:37.508Z"
  },
  "garden": {
    "$oid": "5f04ed124b9065402096412e"
  }
},{
  "_id": {
    "$oid": "5f04ed124b90654020964139"
  },
  "product": {
    "$oid": "5f04ea394b90654020964129"
  },
  "positionX": 5,
  "positionY": 0,
  "timePlanted": {
    "$date": "2020-07-08T16:46:42.359Z"
  },
  "garden": {
    "$oid": "5f04ed124b9065402096412e"
  }
},{
  "_id": {
    "$oid": "5f04ed124b9065402096413b"
  },
  "product": null,
  "positionX": 0,
  "positionY": 1,
  "timePlanted": null,
  "garden": {
    "$oid": "5f04ed124b9065402096412e"
  }
},{
  "_id": {
    "$oid": "5f04ed124b9065402096413d"
  },
  "product": {
    "$oid": "5f04ea6d4b9065402096412a"
  },
  "positionX": 1,
  "positionY": 1,
  "timePlanted": {
    "$date": "2020-07-08T16:11:46.640Z"
  },
  "garden": {
    "$oid": "5f04ed124b9065402096412e"
  }
},{
  "_id": {
    "$oid": "5f04ed124b9065402096413f"
  },
  "product": null,
  "positionX": 2,
  "positionY": 1,
  "timePlanted": null,
  "garden": {
    "$oid": "5f04ed124b9065402096412e"
  }
},{
  "_id": {
    "$oid": "5f04ed124b90654020964141"
  },
  "product": {
    "$oid": "5f04ea874b9065402096412b"
  },
  "positionX": 3,
  "positionY": 1,
  "timePlanted": {
    "$date": "2020-07-08T16:39:22.526Z"
  },
  "garden": {
    "$oid": "5f04ed124b9065402096412e"
  }
},{
  "_id": {
    "$oid": "5f04ed124b90654020964143"
  },
  "product": null,
  "positionX": 4,
  "positionY": 1,
  "timePlanted": null,
  "garden": {
    "$oid": "5f04ed124b9065402096412e"
  }
},{
  "_id": {
    "$oid": "5f04ed124b90654020964145"
  },
  "product": null,
  "positionX": 5,
  "positionY": 1,
  "timePlanted": null,
  "garden": {
    "$oid": "5f04ed124b9065402096412e"
  }
},{
  "_id": {
    "$oid": "5f04ed124b90654020964147"
  },
  "product": null,
  "positionX": 0,
  "positionY": 2,
  "timePlanted": null,
  "garden": {
    "$oid": "5f04ed124b9065402096412e"
  }
},{
  "_id": {
    "$oid": "5f04ed124b90654020964149"
  },
  "product": null,
  "positionX": 1,
  "positionY": 2,
  "timePlanted": null,
  "garden": {
    "$oid": "5f04ed124b9065402096412e"
  }
},{
  "_id": {
    "$oid": "5f04ed124b9065402096414b"
  },
  "product": null,
  "positionX": 2,
  "positionY": 2,
  "timePlanted": null,
  "garden": {
    "$oid": "5f04ed124b9065402096412e"
  }
},{
  "_id": {
    "$oid": "5f04ed124b9065402096414d"
  },
  "product": null,
  "positionX": 3,
  "positionY": 2,
  "timePlanted": null,
  "garden": {
    "$oid": "5f04ed124b9065402096412e"
  }
},{
  "_id": {
    "$oid": "5f04ed124b9065402096414f"
  },
  "product": {
    "$oid": "5f04ea6d4b9065402096412a"
  },
  "positionX": 4,
  "positionY": 2,
  "timePlanted": {
    "$date": "2020-07-08T16:46:55.882Z"
  },
  "garden": {
    "$oid": "5f04ed124b9065402096412e"
  }
},{
  "_id": {
    "$oid": "5f04ed124b90654020964151"
  },
  "product": null,
  "positionX": 5,
  "positionY": 2,
  "timePlanted": null,
  "garden": {
    "$oid": "5f04ed124b9065402096412e"
  }
},{
  "_id": {
    "$oid": "5f04ed124b90654020964153"
  },
  "product": null,
  "positionX": 0,
  "positionY": 3,
  "timePlanted": null,
  "garden": {
    "$oid": "5f04ed124b9065402096412e"
  }
},{
  "_id": {
    "$oid": "5f04ed124b90654020964155"
  },
  "product": null,
  "positionX": 1,
  "positionY": 3,
  "timePlanted": null,
  "garden": {
    "$oid": "5f04ed124b9065402096412e"
  }
},{
  "_id": {
    "$oid": "5f04ed124b90654020964157"
  },
  "product": null,
  "positionX": 2,
  "positionY": 3,
  "timePlanted": null,
  "garden": {
    "$oid": "5f04ed124b9065402096412e"
  }
},{
  "_id": {
    "$oid": "5f04ed124b90654020964159"
  },
  "product": null,
  "positionX": 3,
  "positionY": 3,
  "timePlanted": null,
  "garden": {
    "$oid": "5f04ed124b9065402096412e"
  }
},{
  "_id": {
    "$oid": "5f04ed124b9065402096415b"
  },
  "product": null,
  "positionX": 4,
  "positionY": 3,
  "timePlanted": null,
  "garden": {
    "$oid": "5f04ed124b9065402096412e"
  }
},{
  "_id": {
    "$oid": "5f04ed124b9065402096415d"
  },
  "product": null,
  "positionX": 5,
  "positionY": 3,
  "timePlanted": null,
  "garden": {
    "$oid": "5f04ed124b9065402096412e"
  }
},{
  "_id": {
    "$oid": "5f04ed434b90654020964160"
  },
  "product": null,
  "positionX": 0,
  "positionY": 0,
  "timePlanted": null,
  "garden": {
    "$oid": "5f04ed434b9065402096415f"
  }
},{
  "_id": {
    "$oid": "5f04ed434b90654020964162"
  },
  "product": null,
  "positionX": 1,
  "positionY": 0,
  "timePlanted": null,
  "garden": {
    "$oid": "5f04ed434b9065402096415f"
  }
},{
  "_id": {
    "$oid": "5f04ed434b90654020964164"
  },
  "product": null,
  "positionX": 2,
  "positionY": 0,
  "timePlanted": null,
  "garden": {
    "$oid": "5f04ed434b9065402096415f"
  }
},{
  "_id": {
    "$oid": "5f04ed434b90654020964166"
  },
  "product": null,
  "positionX": 3,
  "positionY": 0,
  "timePlanted": null,
  "garden": {
    "$oid": "5f04ed434b9065402096415f"
  }
},{
  "_id": {
    "$oid": "5f04ed434b90654020964168"
  },
  "product": null,
  "positionX": 4,
  "positionY": 0,
  "timePlanted": null,
  "garden": {
    "$oid": "5f04ed434b9065402096415f"
  }
},{
  "_id": {
    "$oid": "5f04ed434b9065402096416a"
  },
  "product": null,
  "positionX": 5,
  "positionY": 0,
  "timePlanted": null,
  "garden": {
    "$oid": "5f04ed434b9065402096415f"
  }
},{
  "_id": {
    "$oid": "5f04ed434b9065402096416c"
  },
  "product": null,
  "positionX": 6,
  "positionY": 0,
  "timePlanted": null,
  "garden": {
    "$oid": "5f04ed434b9065402096415f"
  }
},{
  "_id": {
    "$oid": "5f04ed434b9065402096416e"
  },
  "product": null,
  "positionX": 7,
  "positionY": 0,
  "timePlanted": null,
  "garden": {
    "$oid": "5f04ed434b9065402096415f"
  }
},{
  "_id": {
    "$oid": "5f04ed434b90654020964170"
  },
  "product": null,
  "positionX": 8,
  "positionY": 0,
  "timePlanted": null,
  "garden": {
    "$oid": "5f04ed434b9065402096415f"
  }
},{
  "_id": {
    "$oid": "5f04ed434b90654020964172"
  },
  "product": null,
  "positionX": 9,
  "positionY": 0,
  "timePlanted": null,
  "garden": {
    "$oid": "5f04ed434b9065402096415f"
  }
},{
  "_id": {
    "$oid": "5f04ed434b90654020964174"
  },
  "product": {
    "$oid": "5f04ea6d4b9065402096412a"
  },
  "positionX": 10,
  "positionY": 0,
  "timePlanted": {
    "$date": "2020-07-08T16:50:30.831Z"
  },
  "garden": {
    "$oid": "5f04ed434b9065402096415f"
  }
},{
  "_id": {
    "$oid": "5f04ed434b90654020964176"
  },
  "product": null,
  "positionX": 11,
  "positionY": 0,
  "timePlanted": null,
  "garden": {
    "$oid": "5f04ed434b9065402096415f"
  }
},{
  "_id": {
    "$oid": "5f04ed434b90654020964178"
  },
  "product": {
    "$oid": "5f04ea394b90654020964129"
  },
  "positionX": 12,
  "positionY": 0,
  "timePlanted": {
    "$date": "2020-07-08T16:50:10.866Z"
  },
  "garden": {
    "$oid": "5f04ed434b9065402096415f"
  }
},{
  "_id": {
    "$oid": "5f04ed434b9065402096417a"
  },
  "product": null,
  "positionX": 13,
  "positionY": 0,
  "timePlanted": null,
  "garden": {
    "$oid": "5f04ed434b9065402096415f"
  }
},{
  "_id": {
    "$oid": "5f04ed434b9065402096417c"
  },
  "product": null,
  "positionX": 14,
  "positionY": 0,
  "timePlanted": null,
  "garden": {
    "$oid": "5f04ed434b9065402096415f"
  }
},{
  "_id": {
    "$oid": "5f04ed434b9065402096417e"
  },
  "product": null,
  "positionX": 0,
  "positionY": 1,
  "timePlanted": null,
  "garden": {
    "$oid": "5f04ed434b9065402096415f"
  }
},{
  "_id": {
    "$oid": "5f04ed434b90654020964180"
  },
  "product": null,
  "positionX": 1,
  "positionY": 1,
  "timePlanted": null,
  "garden": {
    "$oid": "5f04ed434b9065402096415f"
  }
},{
  "_id": {
    "$oid": "5f04ed434b90654020964182"
  },
  "product": null,
  "positionX": 2,
  "positionY": 1,
  "timePlanted": null,
  "garden": {
    "$oid": "5f04ed434b9065402096415f"
  }
},{
  "_id": {
    "$oid": "5f04ed434b90654020964184"
  },
  "product": null,
  "positionX": 3,
  "positionY": 1,
  "timePlanted": null,
  "garden": {
    "$oid": "5f04ed434b9065402096415f"
  }
},{
  "_id": {
    "$oid": "5f04ed434b90654020964186"
  },
  "product": null,
  "positionX": 4,
  "positionY": 1,
  "timePlanted": null,
  "garden": {
    "$oid": "5f04ed434b9065402096415f"
  }
},{
  "_id": {
    "$oid": "5f04ed434b90654020964188"
  },
  "product": null,
  "positionX": 5,
  "positionY": 1,
  "timePlanted": null,
  "garden": {
    "$oid": "5f04ed434b9065402096415f"
  }
},{
  "_id": {
    "$oid": "5f04ed434b9065402096418a"
  },
  "product": {
    "$oid": "5f04ea6d4b9065402096412a"
  },
  "positionX": 6,
  "positionY": 1,
  "timePlanted": {
    "$date": "2020-07-08T16:40:19.284Z"
  },
  "garden": {
    "$oid": "5f04ed434b9065402096415f"
  }
},{
  "_id": {
    "$oid": "5f04ed434b9065402096418c"
  },
  "product": null,
  "positionX": 7,
  "positionY": 1,
  "timePlanted": null,
  "garden": {
    "$oid": "5f04ed434b9065402096415f"
  }
},{
  "_id": {
    "$oid": "5f04ed434b9065402096418e"
  },
  "product": null,
  "positionX": 8,
  "positionY": 1,
  "timePlanted": null,
  "garden": {
    "$oid": "5f04ed434b9065402096415f"
  }
},{
  "_id": {
    "$oid": "5f04ed434b90654020964190"
  },
  "product": null,
  "positionX": 9,
  "positionY": 1,
  "timePlanted": null,
  "garden": {
    "$oid": "5f04ed434b9065402096415f"
  }
},{
  "_id": {
    "$oid": "5f04ed434b90654020964192"
  },
  "product": null,
  "positionX": 10,
  "positionY": 1,
  "timePlanted": null,
  "garden": {
    "$oid": "5f04ed434b9065402096415f"
  }
},{
  "_id": {
    "$oid": "5f04ed434b90654020964194"
  },
  "product": null,
  "positionX": 11,
  "positionY": 1,
  "timePlanted": null,
  "garden": {
    "$oid": "5f04ed434b9065402096415f"
  }
},{
  "_id": {
    "$oid": "5f04ed434b90654020964196"
  },
  "product": null,
  "positionX": 12,
  "positionY": 1,
  "timePlanted": null,
  "garden": {
    "$oid": "5f04ed434b9065402096415f"
  }
},{
  "_id": {
    "$oid": "5f04ed434b90654020964198"
  },
  "product": null,
  "positionX": 13,
  "positionY": 1,
  "timePlanted": null,
  "garden": {
    "$oid": "5f04ed434b9065402096415f"
  }
},{
  "_id": {
    "$oid": "5f04ed434b9065402096419a"
  },
  "product": null,
  "positionX": 14,
  "positionY": 1,
  "timePlanted": null,
  "garden": {
    "$oid": "5f04ed434b9065402096415f"
  }
},{
  "_id": {
    "$oid": "5f04ed434b9065402096419c"
  },
  "product": null,
  "positionX": 0,
  "positionY": 2,
  "timePlanted": null,
  "garden": {
    "$oid": "5f04ed434b9065402096415f"
  }
},{
  "_id": {
    "$oid": "5f04ed434b9065402096419e"
  },
  "product": null,
  "positionX": 1,
  "positionY": 2,
  "timePlanted": null,
  "garden": {
    "$oid": "5f04ed434b9065402096415f"
  }
},{
  "_id": {
    "$oid": "5f04ed434b906540209641a0"
  },
  "product": null,
  "positionX": 2,
  "positionY": 2,
  "timePlanted": null,
  "garden": {
    "$oid": "5f04ed434b9065402096415f"
  }
},{
  "_id": {
    "$oid": "5f04ed434b906540209641a2"
  },
  "product": null,
  "positionX": 3,
  "positionY": 2,
  "timePlanted": null,
  "garden": {
    "$oid": "5f04ed434b9065402096415f"
  }
},{
  "_id": {
    "$oid": "5f04ed434b906540209641a4"
  },
  "product": null,
  "positionX": 4,
  "positionY": 2,
  "timePlanted": null,
  "garden": {
    "$oid": "5f04ed434b9065402096415f"
  }
},{
  "_id": {
    "$oid": "5f04ed434b906540209641a6"
  },
  "product": null,
  "positionX": 5,
  "positionY": 2,
  "timePlanted": null,
  "garden": {
    "$oid": "5f04ed434b9065402096415f"
  }
},{
  "_id": {
    "$oid": "5f04ed434b906540209641a8"
  },
  "product": null,
  "positionX": 6,
  "positionY": 2,
  "timePlanted": null,
  "garden": {
    "$oid": "5f04ed434b9065402096415f"
  }
},{
  "_id": {
    "$oid": "5f04ed434b906540209641aa"
  },
  "product": null,
  "positionX": 7,
  "positionY": 2,
  "timePlanted": null,
  "garden": {
    "$oid": "5f04ed434b9065402096415f"
  }
},{
  "_id": {
    "$oid": "5f04ed434b906540209641ac"
  },
  "product": null,
  "positionX": 8,
  "positionY": 2,
  "timePlanted": null,
  "garden": {
    "$oid": "5f04ed434b9065402096415f"
  }
},{
  "_id": {
    "$oid": "5f04ed434b906540209641ae"
  },
  "product": {
    "$oid": "5f04ea6d4b9065402096412a"
  },
  "positionX": 9,
  "positionY": 2,
  "timePlanted": {
    "$date": "2020-07-08T16:40:22.068Z"
  },
  "garden": {
    "$oid": "5f04ed434b9065402096415f"
  }
},{
  "_id": {
    "$oid": "5f04ed434b906540209641b0"
  },
  "product": null,
  "positionX": 10,
  "positionY": 2,
  "timePlanted": null,
  "garden": {
    "$oid": "5f04ed434b9065402096415f"
  }
},{
  "_id": {
    "$oid": "5f04ed434b906540209641b2"
  },
  "product": null,
  "positionX": 11,
  "positionY": 2,
  "timePlanted": null,
  "garden": {
    "$oid": "5f04ed434b9065402096415f"
  }
},{
  "_id": {
    "$oid": "5f04ed434b906540209641b4"
  },
  "product": {
    "$oid": "5f04ea6d4b9065402096412a"
  },
  "positionX": 12,
  "positionY": 2,
  "timePlanted": {
    "$date": "2020-07-08T16:40:25.668Z"
  },
  "garden": {
    "$oid": "5f04ed434b9065402096415f"
  }
},{
  "_id": {
    "$oid": "5f04ed434b906540209641b6"
  },
  "product": null,
  "positionX": 13,
  "positionY": 2,
  "timePlanted": null,
  "garden": {
    "$oid": "5f04ed434b9065402096415f"
  }
},{
  "_id": {
    "$oid": "5f04ed434b906540209641b8"
  },
  "product": null,
  "positionX": 14,
  "positionY": 2,
  "timePlanted": null,
  "garden": {
    "$oid": "5f04ed434b9065402096415f"
  }
},{
  "_id": {
    "$oid": "5f04ed434b906540209641ba"
  },
  "product": null,
  "positionX": 0,
  "positionY": 3,
  "timePlanted": null,
  "garden": {
    "$oid": "5f04ed434b9065402096415f"
  }
},{
  "_id": {
    "$oid": "5f04ed434b906540209641bc"
  },
  "product": null,
  "positionX": 1,
  "positionY": 3,
  "timePlanted": null,
  "garden": {
    "$oid": "5f04ed434b9065402096415f"
  }
},{
  "_id": {
    "$oid": "5f04ed434b906540209641be"
  },
  "product": null,
  "positionX": 2,
  "positionY": 3,
  "timePlanted": null,
  "garden": {
    "$oid": "5f04ed434b9065402096415f"
  }
},{
  "_id": {
    "$oid": "5f04ed434b906540209641c0"
  },
  "product": {
    "$oid": "5f04ea394b90654020964129"
  },
  "positionX": 3,
  "positionY": 3,
  "timePlanted": {
    "$date": "2020-07-08T16:40:31.052Z"
  },
  "garden": {
    "$oid": "5f04ed434b9065402096415f"
  }
},{
  "_id": {
    "$oid": "5f04ed434b906540209641c2"
  },
  "product": {
    "$oid": "5f04ea394b90654020964129"
  },
  "positionX": 4,
  "positionY": 3,
  "timePlanted": {
    "$date": "2020-07-08T16:38:27.944Z"
  },
  "garden": {
    "$oid": "5f04ed434b9065402096415f"
  }
},{
  "_id": {
    "$oid": "5f04ed434b906540209641c4"
  },
  "product": null,
  "positionX": 5,
  "positionY": 3,
  "timePlanted": null,
  "garden": {
    "$oid": "5f04ed434b9065402096415f"
  }
},{
  "_id": {
    "$oid": "5f04ed434b906540209641c6"
  },
  "product": null,
  "positionX": 6,
  "positionY": 3,
  "timePlanted": null,
  "garden": {
    "$oid": "5f04ed434b9065402096415f"
  }
},{
  "_id": {
    "$oid": "5f04ed434b906540209641c8"
  },
  "product": null,
  "positionX": 7,
  "positionY": 3,
  "timePlanted": null,
  "garden": {
    "$oid": "5f04ed434b9065402096415f"
  }
},{
  "_id": {
    "$oid": "5f04ed434b906540209641ca"
  },
  "product": null,
  "positionX": 8,
  "positionY": 3,
  "timePlanted": null,
  "garden": {
    "$oid": "5f04ed434b9065402096415f"
  }
},{
  "_id": {
    "$oid": "5f04ed434b906540209641cc"
  },
  "product": null,
  "positionX": 9,
  "positionY": 3,
  "timePlanted": null,
  "garden": {
    "$oid": "5f04ed434b9065402096415f"
  }
},{
  "_id": {
    "$oid": "5f04ed434b906540209641ce"
  },
  "product": null,
  "positionX": 10,
  "positionY": 3,
  "timePlanted": null,
  "garden": {
    "$oid": "5f04ed434b9065402096415f"
  }
},{
  "_id": {
    "$oid": "5f04ed434b906540209641d0"
  },
  "product": null,
  "positionX": 11,
  "positionY": 3,
  "timePlanted": null,
  "garden": {
    "$oid": "5f04ed434b9065402096415f"
  }
},{
  "_id": {
    "$oid": "5f04ed434b906540209641d2"
  },
  "product": null,
  "positionX": 12,
  "positionY": 3,
  "timePlanted": null,
  "garden": {
    "$oid": "5f04ed434b9065402096415f"
  }
},{
  "_id": {
    "$oid": "5f04ed434b906540209641d4"
  },
  "product": null,
  "positionX": 13,
  "positionY": 3,
  "timePlanted": null,
  "garden": {
    "$oid": "5f04ed434b9065402096415f"
  }
},{
  "_id": {
    "$oid": "5f04ed434b906540209641d6"
  },
  "product": null,
  "positionX": 14,
  "positionY": 3,
  "timePlanted": null,
  "garden": {
    "$oid": "5f04ed434b9065402096415f"
  }
},{
  "_id": {
    "$oid": "5f04ed434b906540209641d8"
  },
  "product": null,
  "positionX": 0,
  "positionY": 4,
  "timePlanted": null,
  "garden": {
    "$oid": "5f04ed434b9065402096415f"
  }
},{
  "_id": {
    "$oid": "5f04ed434b906540209641da"
  },
  "product": null,
  "positionX": 1,
  "positionY": 4,
  "timePlanted": null,
  "garden": {
    "$oid": "5f04ed434b9065402096415f"
  }
},{
  "_id": {
    "$oid": "5f04ed434b906540209641dc"
  },
  "product": null,
  "positionX": 2,
  "positionY": 4,
  "timePlanted": null,
  "garden": {
    "$oid": "5f04ed434b9065402096415f"
  }
},{
  "_id": {
    "$oid": "5f04ed434b906540209641de"
  },
  "product": null,
  "positionX": 3,
  "positionY": 4,
  "timePlanted": null,
  "garden": {
    "$oid": "5f04ed434b9065402096415f"
  }
},{
  "_id": {
    "$oid": "5f04ed434b906540209641e0"
  },
  "product": null,
  "positionX": 4,
  "positionY": 4,
  "timePlanted": null,
  "garden": {
    "$oid": "5f04ed434b9065402096415f"
  }
},{
  "_id": {
    "$oid": "5f04ed434b906540209641e2"
  },
  "product": null,
  "positionX": 5,
  "positionY": 4,
  "timePlanted": null,
  "garden": {
    "$oid": "5f04ed434b9065402096415f"
  }
},{
  "_id": {
    "$oid": "5f04ed434b906540209641e4"
  },
  "product": null,
  "positionX": 6,
  "positionY": 4,
  "timePlanted": null,
  "garden": {
    "$oid": "5f04ed434b9065402096415f"
  }
},{
  "_id": {
    "$oid": "5f04ed434b906540209641e6"
  },
  "product": null,
  "positionX": 7,
  "positionY": 4,
  "timePlanted": null,
  "garden": {
    "$oid": "5f04ed434b9065402096415f"
  }
},{
  "_id": {
    "$oid": "5f04ed434b906540209641e8"
  },
  "product": null,
  "positionX": 8,
  "positionY": 4,
  "timePlanted": null,
  "garden": {
    "$oid": "5f04ed434b9065402096415f"
  }
},{
  "_id": {
    "$oid": "5f04ed434b906540209641ea"
  },
  "product": null,
  "positionX": 9,
  "positionY": 4,
  "timePlanted": null,
  "garden": {
    "$oid": "5f04ed434b9065402096415f"
  }
},{
  "_id": {
    "$oid": "5f04ed434b906540209641ec"
  },
  "product": null,
  "positionX": 10,
  "positionY": 4,
  "timePlanted": null,
  "garden": {
    "$oid": "5f04ed434b9065402096415f"
  }
},{
  "_id": {
    "$oid": "5f04ed434b906540209641ee"
  },
  "product": null,
  "positionX": 11,
  "positionY": 4,
  "timePlanted": null,
  "garden": {
    "$oid": "5f04ed434b9065402096415f"
  }
},{
  "_id": {
    "$oid": "5f04ed434b906540209641f0"
  },
  "product": null,
  "positionX": 12,
  "positionY": 4,
  "timePlanted": null,
  "garden": {
    "$oid": "5f04ed434b9065402096415f"
  }
},{
  "_id": {
    "$oid": "5f04ed434b906540209641f2"
  },
  "product": null,
  "positionX": 13,
  "positionY": 4,
  "timePlanted": null,
  "garden": {
    "$oid": "5f04ed434b9065402096415f"
  }
},{
  "_id": {
    "$oid": "5f04ed434b906540209641f4"
  },
  "product": null,
  "positionX": 14,
  "positionY": 4,
  "timePlanted": null,
  "garden": {
    "$oid": "5f04ed434b9065402096415f"
  }
}]